<?xml version="1.0"?>
<AppInfo>
  <About>
    <Purpose>CDROM manager</Purpose>
    <Authors>Stephen Watson</Authors>
    <License>GNU General Public License</License>
    <Homepage>http://www.kerofin.demon.co.uk/rox/</Homepage>
  </About>
<Summary>Manage the CDROM drive on a Sun Solaris system.</Summary>
<AppMenu>
  <Item label="View CDROM contents" option="--view"/>
  <Item label="Mount CDROM" option="--mount"/>
  <Item label="Dismount and eject CDROM" option="--dismount"/>
</AppMenu>
</AppInfo>
